placafipy/__init__.py
PlacaFipy-1.0.3.dist-info/LICENSE
PlacaFipy-1.0.3.dist-info/METADATA
PlacaFipy-1.0.3.dist-info/WHEEL
PlacaFipy-1.0.3.dist-info/top_level.txt
PlacaFipy-1.0.3.dist-info/RECORD
